mcp_timer/__init__.py
mcp_timer/__main__.py
mcp_timer-0.1.1.dist-info/METADATA
mcp_timer-0.1.1.dist-info/WHEEL
mcp_timer-0.1.1.dist-info/entry_points.txt
mcp_timer-0.1.1.dist-info/RECORD
