Metadata-Version: 2.4
Name: mcp-timer
Version: 0.1.1
Summary: MCP Timer Server - Wait and scheduled timing tools for AI agents
Project-URL: Homepage, https://github.com/aleck31/mcp-timer
License-Expression: MIT
Keywords: agent,ai,mcp,timer
Classifier: Development Status :: 4 - Beta
Classifier: Intended Audience :: Developers
Classifier: License :: OSI Approved :: MIT License
Classifier: Programming Language :: Python :: 3
Requires-Python: >=3.10
Requires-Dist: mcp[cli]>=1.0.0
